Metadata-Version: 1.0
Name: rvd-distributions
Version: 0.1
Summary: Gaussian distributions
Home-page: UNKNOWN
Author: Renan Vieira Dias
Author-email: renanvieiradias@gmail.com
License: UNKNOWN
Platform: UNKNOWN
